MANIFEST.in
setup.py
bin/ephys_viz
ephys_viz/BaseWidget.py
ephys_viz/__init__.py
ephys_viz/_version.py
ephys_viz/all_widgets.py
ephys_viz/host_widget.py
ephys_viz/init.py
ephys_viz/reactopya_serialize.py
ephys_viz/reactopyacolabwidget.py
ephys_viz/reactopyacomponent.py
ephys_viz/reactopyaelectronwidget.py
ephys_viz/reactopyahostedwidget.py
ephys_viz/shellscript.py
ephys_viz.egg-info/PKG-INFO
ephys_viz.egg-info/SOURCES.txt
ephys_viz.egg-info/dependency_links.txt
ephys_viz.egg-info/requires.txt
ephys_viz.egg-info/top_level.txt
ephys_viz/dist/bundle.js
ephys_viz/electron/src/ReactopyaModel.js
ephys_viz/electron/src/index.js
ephys_viz/electron/src/preload.js
ephys_viz/electron/web/index.html
ephys_viz/host_widget/dist/bundle.js
ephys_viz/widgets/__init__.py
ephys_viz/widgets/create_sync.py
ephys_viz/widgets/index.js
ephys_viz/widgets/jupyter.py
ephys_viz/widgets/Accordion/Accordion.js
ephys_viz/widgets/Accordion/Accordion.json
ephys_viz/widgets/Accordion/Accordion.py
ephys_viz/widgets/Accordion/AccordionStyle.css
ephys_viz/widgets/Accordion/__init__.py
ephys_viz/widgets/Accordion/__pycache__/Accordion.cpython-37.pyc
ephys_viz/widgets/Accordion/__pycache__/__init__.cpython-37.pyc
ephys_viz/widgets/Autocorrelograms/Autocorrelograms.js
ephys_viz/widgets/Autocorrelograms/Autocorrelograms.json
ephys_viz/widgets/Autocorrelograms/Autocorrelograms.py
ephys_viz/widgets/Autocorrelograms/__init__.py
ephys_viz/widgets/Autocorrelograms/examples.py
ephys_viz/widgets/Autocorrelograms/__pycache__/Autocorrelograms.cpython-37.pyc
ephys_viz/widgets/Autocorrelograms/__pycache__/__init__.cpython-37.pyc
ephys_viz/widgets/Autocorrelograms/__pycache__/examples.cpython-37.pyc
ephys_viz/widgets/CorticalSurface/CorticalSurface.js
ephys_viz/widgets/CorticalSurface/CorticalSurface.json
ephys_viz/widgets/CorticalSurface/CorticalSurface.py
ephys_viz/widgets/CorticalSurface/__init__.py
ephys_viz/widgets/CorticalSurface/examples.py
ephys_viz/widgets/CorticalSurface/__pycache__/CorticalSurface.cpython-37.pyc
ephys_viz/widgets/CorticalSurface/__pycache__/__init__.cpython-37.pyc
ephys_viz/widgets/CorticalSurface/__pycache__/examples.cpython-37.pyc
